okta_expression_parser/__init__.py
okta_expression_parser/expression_classes/__init__.py
okta_expression_parser/expression_classes/arrays.py
okta_expression_parser/expression_classes/convert.py
okta_expression_parser/expression_classes/groups.py
okta_expression_parser/expression_classes/iso3166convert.py
okta_expression_parser/expression_classes/string.py
okta_expression_parser/lexer.py
okta_expression_parser/parser.py
okta_expression_parser-0.4.2.dist-info/METADATA
okta_expression_parser-0.4.2.dist-info/WHEEL
okta_expression_parser-0.4.2.dist-info/RECORD
